Metadata-Version: 2.1
Name: cesr
Version: 0.0.1
Summary: CESR: Composable Event Streaming Representation
Home-page: https://github.com/WebOfTrust/cesrpy
Author: Samuel M. Smith
Author-email: sam@samuelsmith.org
License: Apache Software License 2.0
Project-URL: Issue Tracker, https://github.com/WebOfTrust/cesrpy/issues
Keywords: secure attribution,authentic data,discovery,resolver
Classifier: Development Status :: 3 - Alpha
Classifier: Intended Audience :: Developers
Classifier: License :: OSI Approved :: Apache Software License
Classifier: Operating System :: Unix
Classifier: Operating System :: POSIX
Classifier: Operating System :: Microsoft :: Windows
Classifier: Programming Language :: Python :: 3.10
Classifier: Programming Language :: Python :: Implementation :: CPython
Classifier: Topic :: Utilities
Requires-Python: >=3.10.4
License-File: LICENSE
